{
  "api": {
    "wedding": {
      "dependsOn": [],
      "output": {
        "authConfig": {
          "additionalAuthenticationProviders": [],
          "defaultAuthentication": {
            "apiKeyConfig": {
              "apiKeyExpirationDate": "2025-01-07T13:58:26.192Z",
              "apiKeyExpirationDays": 365,
              "description": ""
            },
            "authenticationType": "API_KEY"
          }
        }
      },
      "providerPlugin": "awscloudformation",
      "service": "AppSync"
    }
  }
}