{
  "api": {
    "wedding": {
      "dependsOn": [],
      "output": {
        "authConfig": {
          "additionalAuthenticationProviders": [],
          "defaultAuthentication": {
            "authenticationType": "API_KEY",
            "apiKeyConfig": {
              "apiKeyExpirationDays": 365,
              "apiKeyExpirationDate": "2024-08-07T20:35:55.344Z",
              "description": ""
            }
          }
        }
      },
      "providerPlugin": "awscloudformation",
      "service": "AppSync"
    }
  }
}